tg_logger/__init__.py
tg_logger/__version__.py
tg_logger/settings.py
tg_logger/sync_logger/__init__.py
tg_logger/sync_logger/logger_warner.py
tg_logger/sync_logger/loggers.py
logger_tg-0.0.94.dist-info/LICENSE
logger_tg-0.0.94.dist-info/METADATA
logger_tg-0.0.94.dist-info/WHEEL
logger_tg-0.0.94.dist-info/top_level.txt
logger_tg-0.0.94.dist-info/RECORD
