Metadata-Version: 2.1
Name: logger-tg
Version: 0.0.94
Summary: Logger with easy setup and sending errors to telegram
Home-page: https://github.com/Nezhinskiy/logger-tg
Author: Nezhinskiy
Author-email: mikhail.nezhinsky@gmail.com
License: MIT
Keywords: logger,logging,telegram,telegram_logger,tg_logger,python
Classifier: License :: OSI Approved :: MIT License
Classifier: Programming Language :: Python
Classifier: Programming Language :: Python :: 3
Classifier: Programming Language :: Python :: 3.7
Classifier: Programming Language :: Python :: 3.8
Classifier: Programming Language :: Python :: 3.9
Classifier: Programming Language :: Python :: 3.10
Classifier: Programming Language :: Python :: Implementation :: CPython
License-File: LICENSE
Requires-Dist: pyTelegramBotAPI >=4.14.0
